mockthink/__init__.py
mockthink/ast.py
mockthink/ast_base.py
mockthink/db.py
mockthink/joins.py
mockthink/rql_rewrite.py
mockthink/rtime.py
mockthink/scope.py
mockthink/util.py
mockthink/version.py
mockthink-0.9.6.dist-info/DESCRIPTION.rst
mockthink-0.9.6.dist-info/METADATA
mockthink-0.9.6.dist-info/RECORD
mockthink-0.9.6.dist-info/WHEEL
mockthink-0.9.6.dist-info/metadata.json
mockthink-0.9.6.dist-info/top_level.txt
mockthink-0.9.6.dist-info/zip-safe
