Metadata-Version: 2.0
Name: mockthink
Version: 0.9.6
Summary: A pure-python in-memory mock of rethinkdb
Home-page: http://github.com/scivey/mockthink
Author: Scott Ivey
Author-email: scott.ivey@gmail.com
License: UNKNOWN
Platform: UNKNOWN
Requires-Dist: rethinkdb (>=2.2.0,<2.3.0)
Requires-Dist: dateutils
Requires-Dist: future
